freeagent_api/Pipfile
freeagent_api/__init__.py
freeagent_api/accounting_category.py
freeagent_api/bank_account.py
freeagent_api/bank_transaction.py
freeagent_api/bank_transaction_explanation.py
freeagent_api/base_object.py
freeagent_api/company.py
freeagent_api/contact.py
freeagent_api/invoice.py
freeagent_api/invoice_item.py
freeagent_api/oauth.py
freeagent_api/project.py
freeagent_api/user.py
freeagent_api-0.5.0.dist-info/METADATA
freeagent_api-0.5.0.dist-info/WHEEL
freeagent_api-0.5.0.dist-info/licenses/LICENSE
freeagent_api-0.5.0.dist-info/RECORD
