Metadata-Version: 2.1
Name: freeagent_api
Version: 0.5.0
Summary: Interface to the FreeAgent accounting software API
Project-URL: Bug Tracker, https://gitlab.com/inutt/python-freeagent-api/-/issues
Project-URL: Repository, https://gitlab.com/inutt/python-freeagent-api
Author-email: Richard Davis <inutt.dev@gmail.com>
License:                     GNU AFFERO GENERAL PUBLIC LICENSE
License-File: LICENSE
Classifier: Development Status :: 3 - Alpha
Classifier: License :: OSI Approved :: GNU Affero General Public License v3 or later (AGPLv3+)
Classifier: Operating System :: OS Independent
Classifier: Programming Language :: Python :: 3
Classifier: Topic :: Internet
Requires-Python: >=3.11
Requires-Dist: requests-oauth2client
